pept/__init__.py
pept/__version__.py
pept/base/__init__.py
pept/base/iterable_samples.py
pept/base/line_data.py
pept/base/pipelines.py
pept/base/pixels.py
pept/base/point_data.py
pept/base/sampling_extensions.c
pept/base/sampling_extensions.cp310-win_amd64.pyd
pept/base/sampling_extensions.pyx
pept/base/utilities.py
pept/base/voxels.py
pept/plots/__init__.py
pept/plots/plotly_grapher.py
pept/plots/plotly_grapher2d.py
pept/processing/__init__.py
pept/processing/grids.py
pept/processing/mixing.py
pept/scanners/__init__.py
pept/scanners/modular_camera/__init__.py
pept/scanners/modular_camera/modular_camera.py
pept/scanners/modular_camera/extensions/get_pept_event.c
pept/scanners/modular_camera/extensions/get_pept_event.cp310-win_amd64.pyd
pept/scanners/modular_camera/extensions/get_pept_event.pyx
pept/scanners/modular_camera/extensions/get_pept_event_ext.c
pept/scanners/modular_camera/extensions/get_pept_event_ext.h
pept/scanners/parallel_screens/__init__.py
pept/scanners/parallel_screens/adac_forte.py
pept/scanners/parallel_screens/parallel_screens.py
pept/scanners/parallel_screens/extensions/__init__.py
pept/scanners/parallel_screens/extensions/binary_converter.c
pept/scanners/parallel_screens/extensions/binary_converter.cp310-win_amd64.pyd
pept/scanners/parallel_screens/extensions/binary_converter.pyx
pept/scanners/parallel_screens/extensions/binary_converter_ext.c
pept/scanners/parallel_screens/extensions/binary_converter_ext.h
pept/simulation/__init__.py
pept/simulation/peptsim.py
pept/tracking/__init__.py
pept/tracking/post.py
pept/tracking/space_transformers.py
pept/tracking/transformers.py
pept/tracking/birmingham_method/__init__.py
pept/tracking/birmingham_method/birmingham_method.py
pept/tracking/birmingham_method/extensions/birmingham_method.c
pept/tracking/birmingham_method/extensions/birmingham_method.cp310-win_amd64.pyd
pept/tracking/birmingham_method/extensions/birmingham_method.pyx
pept/tracking/birmingham_method/extensions/birmingham_method_ext.c
pept-0.5.1.dist-info/LICENSE
pept-0.5.1.dist-info/METADATA
pept-0.5.1.dist-info/WHEEL
pept-0.5.1.dist-info/top_level.txt
pept-0.5.1.dist-info/RECORD
