Metadata-Version: 2.1
Name: pept
Version: 0.5.1
Summary: A Python library that unifies Positron Emission Particle Tracking (PEPT) research, including tracking, simulation, data analysis and visualisation tools.
Home-page: https://github.com/uob-positron-imaging-centre/pept
Author: Andrei Leonard Nicusan
Author-email: a.l.nicusan@bham.ac.uk
License: GNU
Keywords: pept positron emission particle tracking
Classifier: License :: OSI Approved :: GNU General Public License v3 or later (GPLv3+)
Classifier: Development Status :: 4 - Beta
Classifier: Intended Audience :: Science/Research
Classifier: Natural Language :: English
Classifier: Programming Language :: Python
Classifier: Programming Language :: Python :: 3
Classifier: Programming Language :: Python :: 3.7
Classifier: Programming Language :: Python :: 3.8
Classifier: Programming Language :: Python :: 3.9
Classifier: Programming Language :: Python :: 3.10
Classifier: Programming Language :: Python :: Implementation :: CPython
Classifier: Programming Language :: Cython
Classifier: Programming Language :: C
Classifier: Programming Language :: C++
Classifier: Topic :: Scientific/Engineering
Classifier: Topic :: Scientific/Engineering :: Artificial Intelligence
Classifier: Topic :: Scientific/Engineering :: Physics
Classifier: Topic :: Scientific/Engineering :: Information Analysis
Classifier: Topic :: Scientific/Engineering :: Visualization
Classifier: Topic :: Software Development :: Libraries :: Python Modules
Requires-Python: >=3.7.0
License-File: LICENSE
Requires-Dist: Cython (>=0.29.16)
Requires-Dist: scipy (>=1.4.1)
Requires-Dist: hdbscan (>=0.8.26)
Requires-Dist: numpy (>=1.18.3)
Requires-Dist: joblib (<1.2,>=0.14.1)
Requires-Dist: matplotlib (>=3.2.1)
Requires-Dist: plotly (>=4.4.1)
Requires-Dist: tqdm (>=4.41.1)
Requires-Dist: pandas (>=1.0.3)
Requires-Dist: cma (>=3.0.3)
Requires-Dist: natsort (>=5.5.0)
Requires-Dist: konigcell (>=0.2.0)
Provides-Extra: docs
Requires-Dist: Sphinx (>=4.1) ; extra == 'docs'
Requires-Dist: numpydoc (>=1.1) ; extra == 'docs'
Requires-Dist: ipython (>=5.5.0) ; extra == 'docs'
Requires-Dist: pydata-sphinx-theme (>=0.6.3) ; extra == 'docs'
Requires-Dist: numba (>=0.50.0) ; extra == 'docs'
Requires-Dist: pytest (>=3.6.4) ; extra == 'docs'
Requires-Dist: myst-parser (>=0.18) ; extra == 'docs'
